richclub/__init__.py
richclub/rich_club_coefficient_degree.py
richclubv3-1.0.0.dev1.dist-info/DESCRIPTION.rst
richclubv3-1.0.0.dev1.dist-info/METADATA
richclubv3-1.0.0.dev1.dist-info/RECORD
richclubv3-1.0.0.dev1.dist-info/WHEEL
richclubv3-1.0.0.dev1.dist-info/metadata.json
richclubv3-1.0.0.dev1.dist-info/top_level.txt
